deepops/__init__.py
deepops/diff.py
deepops/filter.py
deepops/get.py
deepops/merge.py
deepops/path.py
deepops/removeitems.py
deepops/setdefault.py
test_deepops/__init__.py
test_deepops/__main__.py
test_deepops/test_deepops.py
deepops-1.8.dist-info/LICENSE
deepops-1.8.dist-info/METADATA
deepops-1.8.dist-info/WHEEL
deepops-1.8.dist-info/top_level.txt
deepops-1.8.dist-info/RECORD
